meta_di/__init__.py
meta_di/builder.py
meta_di/code_formatter.py
meta_di/code_generator.py
meta_di/container_proto.py
meta_di/exceptions.py
meta_di/inspector.py
meta_di/service_descriptor.py
meta_di/typing.py
meta_di-0.0.1.dist-info/METADATA
meta_di-0.0.1.dist-info/WHEEL
meta_di-0.0.1.dist-info/licenses/LICENSE
meta_di-0.0.1.dist-info/RECORD
