Metadata-Version: 2.1
Name: meta-di
Version: 0.0.1
Summary: DI container using meta programming
Project-URL: Homepage, https://github.com/GabrielCappelli/meta-di
Project-URL: Documentation, https://github.com/GabrielCappelli/meta-di
Project-URL: Source, https://github.com/GabrielCappelli/meta-di
Author-email: Gabriel Cappelli <6148081+GabrielCappelli@users.noreply.github.com>
License-Expression: MIT
License-File: LICENSE
Requires-Python: >=3.8
